[
    {
        "videoId": "C9KF6EdS9-8",
        "url": "https://r1---sn-n4v7sn7l.googlevideo.com/videoplayback?key=yt6&pl=43&ipbits=0&initcwndbps=795000&signature=95390C86FE8AF66A83DBE96ABD22B27B48C4F2E0.DC883FFFF3F113008F7A4EF87E7A97F3322F3D24&keepalive=yes&requiressl=yes&ei=RvVeWoyeJMq3-wPo-KG4DA&itag=264&source=youtube&sparams=aitags%2Cclen%2Cdur%2Cei%2Cgir%2Cid%2Cinitcwndbps%2Cip%2Cipbits%2Citag%2Ckeepalive%2Clmt%2Cmime%2Cmm%2Cmn%2Cms%2Cmv%2Cpl%2Crequiressl%2Csource%2Cexpire&dur=141.407&id=o-AID3YgNaOdm4IPN9R62_PL9aH066Y7LZkl6mkyVTrDz9&mn=sn-n4v7sn7l&gir=yes&mm=31&ms=au&mv=m&mt=1516172505&mime=video%2Fmp4&ip=2600%3A1700%3A5b20%3A6ae0%3A68e4%3A5be%3Ad182%3Aa663&clen=183160531&aitags=133%2C134%2C135%2C136%2C137%2C160%2C242%2C243%2C244%2C247%2C248%2C264%2C266%2C271%2C278%2C313&expire=1516194214&lmt=1499039888607901&ratebypass=yes\n",
        "codecs": "avc1.640032\",itag=27",
        "itag": "264",
        "indexRange": "0-1162",
        "sidx": {
            "version": 0,
            "timescale": 90000,
            "earliestPresentationTime": 0,
            "firstOffset": 1163,
            "referenceCount": 27,
            "references": [
                {
                    "size": 6915303,
                    "type": 0,
                    "offset": 1163,
                    "duration": 480480,
                    "time": 0,
                    "timescale": 90000,
                    "mediaRange": "1163-6916465",
                    "startRange": 1163,
                    "endRange": 6916465,
                    "durationSec": 5.338666666666667,
                    "startTimeSec": 0
                },
                {
                    "size": 6926667,
                    "type": 0,
                    "offset": 6916466,
                    "duration": 480480,
                    "time": 480480,
                    "timescale": 90000,
                    "mediaRange": "6916466-13843132",
                    "startRange": 6916466,
                    "endRange": 13843132,
                    "durationSec": 5.338666666666667,
                    "startTimeSec": 5.338666666666667
                },
                {
                    "size": 6908004,
                    "type": 0,
                    "offset": 13843133,
                    "duration": 480480,
                    "time": 960960,
                    "timescale": 90000,
                    "mediaRange": "13843133-20751136",
                    "startRange": 13843133,
                    "endRange": 20751136,
                    "durationSec": 5.338666666666667,
                    "startTimeSec": 10.677333333333333
                },
                {
                    "size": 6911596,
                    "type": 0,
                    "offset": 20751137,
                    "duration": 480480,
                    "time": 1441440,
                    "timescale": 90000,
                    "mediaRange": "20751137-27662732",
                    "startRange": 20751137,
                    "endRange": 27662732,
                    "durationSec": 5.338666666666667,
                    "startTimeSec": 16.016
                },
                {
                    "size": 6912597,
                    "type": 0,
                    "offset": 27662733,
                    "duration": 480480,
                    "time": 1921920,
                    "timescale": 90000,
                    "mediaRange": "27662733-34575329",
                    "startRange": 27662733,
                    "endRange": 34575329,
                    "durationSec": 5.338666666666667,
                    "startTimeSec": 21.354666666666667
                },
                {
                    "size": 6940436,
                    "type": 0,
                    "offset": 34575330,
                    "duration": 480480,
                    "time": 2402400,
                    "timescale": 90000,
                    "mediaRange": "34575330-41515765",
                    "startRange": 34575330,
                    "endRange": 41515765,
                    "durationSec": 5.338666666666667,
                    "startTimeSec": 26.69333333333333
                },
                {
                    "size": 6905768,
                    "type": 0,
                    "offset": 41515766,
                    "duration": 480480,
                    "time": 2882880,
                    "timescale": 90000,
                    "mediaRange": "41515766-48421533",
                    "startRange": 41515766,
                    "endRange": 48421533,
                    "durationSec": 5.338666666666667,
                    "startTimeSec": 32.032
                },
                {
                    "size": 6891318,
                    "type": 0,
                    "offset": 48421534,
                    "duration": 480480,
                    "time": 3363360,
                    "timescale": 90000,
                    "mediaRange": "48421534-55312851",
                    "startRange": 48421534,
                    "endRange": 55312851,
                    "durationSec": 5.338666666666667,
                    "startTimeSec": 37.370666666666665
                },
                {
                    "size": 6911003,
                    "type": 0,
                    "offset": 55312852,
                    "duration": 480480,
                    "time": 3843840,
                    "timescale": 90000,
                    "mediaRange": "55312852-62223854",
                    "startRange": 55312852,
                    "endRange": 62223854,
                    "durationSec": 5.338666666666667,
                    "startTimeSec": 42.70933333333333
                },
                {
                    "size": 6902591,
                    "type": 0,
                    "offset": 62223855,
                    "duration": 480480,
                    "time": 4324320,
                    "timescale": 90000,
                    "mediaRange": "62223855-69126445",
                    "startRange": 62223855,
                    "endRange": 69126445,
                    "durationSec": 5.338666666666667,
                    "startTimeSec": 48.048
                },
                {
                    "size": 6903639,
                    "type": 0,
                    "offset": 69126446,
                    "duration": 480480,
                    "time": 4804800,
                    "timescale": 90000,
                    "mediaRange": "69126446-76030084",
                    "startRange": 69126446,
                    "endRange": 76030084,
                    "durationSec": 5.338666666666667,
                    "startTimeSec": 53.38666666666666
                },
                {
                    "size": 6945623,
                    "type": 0,
                    "offset": 76030085,
                    "duration": 480480,
                    "time": 5285280,
                    "timescale": 90000,
                    "mediaRange": "76030085-82975707",
                    "startRange": 76030085,
                    "endRange": 82975707,
                    "durationSec": 5.338666666666667,
                    "startTimeSec": 58.72533333333333
                },
                {
                    "size": 6902698,
                    "type": 0,
                    "offset": 82975708,
                    "duration": 480480,
                    "time": 5765760,
                    "timescale": 90000,
                    "mediaRange": "82975708-89878405",
                    "startRange": 82975708,
                    "endRange": 89878405,
                    "durationSec": 5.338666666666667,
                    "startTimeSec": 64.064
                },
                {
                    "size": 6908414,
                    "type": 0,
                    "offset": 89878406,
                    "duration": 480480,
                    "time": 6246240,
                    "timescale": 90000,
                    "mediaRange": "89878406-96786819",
                    "startRange": 89878406,
                    "endRange": 96786819,
                    "durationSec": 5.338666666666667,
                    "startTimeSec": 69.40266666666666
                },
                {
                    "size": 6903867,
                    "type": 0,
                    "offset": 96786820,
                    "duration": 480480,
                    "time": 6726720,
                    "timescale": 90000,
                    "mediaRange": "96786820-103690686",
                    "startRange": 96786820,
                    "endRange": 103690686,
                    "durationSec": 5.338666666666667,
                    "startTimeSec": 74.74133333333333
                },
                {
                    "size": 6951641,
                    "type": 0,
                    "offset": 103690687,
                    "duration": 480480,
                    "time": 7207200,
                    "timescale": 90000,
                    "mediaRange": "103690687-110642327",
                    "startRange": 103690687,
                    "endRange": 110642327,
                    "durationSec": 5.338666666666667,
                    "startTimeSec": 80.08
                },
                {
                    "size": 6905410,
                    "type": 0,
                    "offset": 110642328,
                    "duration": 480480,
                    "time": 7687680,
                    "timescale": 90000,
                    "mediaRange": "110642328-117547737",
                    "startRange": 110642328,
                    "endRange": 117547737,
                    "durationSec": 5.338666666666667,
                    "startTimeSec": 85.41866666666667
                },
                {
                    "size": 6916984,
                    "type": 0,
                    "offset": 117547738,
                    "duration": 480480,
                    "time": 8168160,
                    "timescale": 90000,
                    "mediaRange": "117547738-124464721",
                    "startRange": 117547738,
                    "endRange": 124464721,
                    "durationSec": 5.338666666666667,
                    "startTimeSec": 90.75733333333334
                },
                {
                    "size": 6899551,
                    "type": 0,
                    "offset": 124464722,
                    "duration": 480480,
                    "time": 8648640,
                    "timescale": 90000,
                    "mediaRange": "124464722-131364272",
                    "startRange": 124464722,
                    "endRange": 131364272,
                    "durationSec": 5.338666666666667,
                    "startTimeSec": 96.096
                },
                {
                    "size": 6908845,
                    "type": 0,
                    "offset": 131364273,
                    "duration": 480480,
                    "time": 9129120,
                    "timescale": 90000,
                    "mediaRange": "131364273-138273117",
                    "startRange": 131364273,
                    "endRange": 138273117,
                    "durationSec": 5.338666666666667,
                    "startTimeSec": 101.43466666666667
                },
                {
                    "size": 6910276,
                    "type": 0,
                    "offset": 138273118,
                    "duration": 480480,
                    "time": 9609600,
                    "timescale": 90000,
                    "mediaRange": "138273118-145183393",
                    "startRange": 138273118,
                    "endRange": 145183393,
                    "durationSec": 5.338666666666667,
                    "startTimeSec": 106.77333333333333
                },
                {
                    "size": 6924180,
                    "type": 0,
                    "offset": 145183394,
                    "duration": 480480,
                    "time": 10090080,
                    "timescale": 90000,
                    "mediaRange": "145183394-152107573",
                    "startRange": 145183394,
                    "endRange": 152107573,
                    "durationSec": 5.338666666666667,
                    "startTimeSec": 112.112
                },
                {
                    "size": 6918678,
                    "type": 0,
                    "offset": 152107574,
                    "duration": 480480,
                    "time": 10570560,
                    "timescale": 90000,
                    "mediaRange": "152107574-159026251",
                    "startRange": 152107574,
                    "endRange": 159026251,
                    "durationSec": 5.338666666666667,
                    "startTimeSec": 117.45066666666666
                },
                {
                    "size": 6918792,
                    "type": 0,
                    "offset": 159026252,
                    "duration": 480480,
                    "time": 11051040,
                    "timescale": 90000,
                    "mediaRange": "159026252-165945043",
                    "startRange": 159026252,
                    "endRange": 165945043,
                    "durationSec": 5.338666666666667,
                    "startTimeSec": 122.78933333333333
                },
                {
                    "size": 6906454,
                    "type": 0,
                    "offset": 165945044,
                    "duration": 480480,
                    "time": 11531520,
                    "timescale": 90000,
                    "mediaRange": "165945044-172851497",
                    "startRange": 165945044,
                    "endRange": 172851497,
                    "durationSec": 5.338666666666667,
                    "startTimeSec": 128.128
                },
                {
                    "size": 6959635,
                    "type": 0,
                    "offset": 172851498,
                    "duration": 480480,
                    "time": 12012000,
                    "timescale": 90000,
                    "mediaRange": "172851498-179811132",
                    "startRange": 172851498,
                    "endRange": 179811132,
                    "durationSec": 5.338666666666667,
                    "startTimeSec": 133.46666666666667
                },
                {
                    "size": 3349398,
                    "type": 0,
                    "offset": 179811133,
                    "duration": 234234,
                    "time": 12492480,
                    "timescale": 90000,
                    "mediaRange": "179811133-183160530",
                    "startRange": 179811133,
                    "endRange": 183160530,
                    "durationSec": 2.6026,
                    "startTimeSec": 138.80533333333332
                }
            ]
        }
    }
]