[
    {
        "videoId": "R4-XIR7b-Qo",
        "url": "https://r3---sn-o097znl6.googlevideo.com/videoplayback?beids=%5B9466591%5D&source=youtube&dur=448.447&lmt=1500665695827950&sparams=aitags%2Cclen%2Cdur%2Cei%2Cgir%2Cid%2Cinitcwndbps%2Cip%2Cipbits%2Citag%2Ckeepalive%2Clmt%2Cmime%2Cmm%2Cmn%2Cms%2Cmv%2Cpcm2%2Cpl%2Crequiressl%2Csource%2Cxtags%2Cexpire&key=yt6&mime=video%2Fmp4&pl=43&expire=1516182733&clen=1208049213&keepalive=yes&mm=31&mn=sn-o097znl6&mt=1516161053&mv=m&ei=bcheWpHYE9CBqgW4jrqgDg&ms=au&itag=266&pcm2=yes&xtags=vproj%3Dmesh&ipbits=0&requiressl=yes&gir=yes&signature=50937A7519889708273694B48A110C8834329893.7BBD615CFB8FEC6138E78DE56256EF8993212C4D&aitags=133%2C134%2C135%2C136%2C137%2C160%2C242%2C243%2C244%2C247%2C248%2C264%2C266%2C271%2C278%2C313&ip=2600%3A1700%3A5b20%3A6ae0%3Aad03%3A9df3%3Af4fe%3A12c9&initcwndbps=748750&id=o-AEdgGtnAyuOiU-rcVXZ0lyp5CMFHFB3wpKd6VVeXfoIi&ratebypass=yes\n",
        "codecs": "avc1.640033",
        "itag": "266",
        "indexRange": "0-4316",
        "sidx": {
            "version": 0,
            "timescale": 30000,
            "earliestPresentationTime": 0,
            "firstOffset": 4317,
            "referenceCount": 84,
            "references": [
                {
                    "size": 14623688,
                    "type": 0,
                    "offset": 4317,
                    "duration": 160160,
                    "time": 0,
                    "timescale": 30000,
                    "mediaRange": "4317-14628004",
                    "startRange": 4317,
                    "endRange": 14628004,
                    "durationSec": 5.338666666666667,
                    "startTimeSec": 0
                },
                {
                    "size": 14671669,
                    "type": 0,
                    "offset": 14628005,
                    "duration": 160160,
                    "time": 160160,
                    "timescale": 30000,
                    "mediaRange": "14628005-29299673",
                    "startRange": 14628005,
                    "endRange": 29299673,
                    "durationSec": 5.338666666666667,
                    "startTimeSec": 5.338666666666667
                },
                {
                    "size": 14646229,
                    "type": 0,
                    "offset": 29299674,
                    "duration": 160160,
                    "time": 320320,
                    "timescale": 30000,
                    "mediaRange": "29299674-43945902",
                    "startRange": 29299674,
                    "endRange": 43945902,
                    "durationSec": 5.338666666666667,
                    "startTimeSec": 10.677333333333333
                },
                {
                    "size": 12874947,
                    "type": 0,
                    "offset": 43945903,
                    "duration": 160160,
                    "time": 480480,
                    "timescale": 30000,
                    "mediaRange": "43945903-56820849",
                    "startRange": 43945903,
                    "endRange": 56820849,
                    "durationSec": 5.338666666666667,
                    "startTimeSec": 16.016
                },
                {
                    "size": 10291199,
                    "type": 0,
                    "offset": 56820850,
                    "duration": 160160,
                    "time": 640640,
                    "timescale": 30000,
                    "mediaRange": "56820850-67112048",
                    "startRange": 56820850,
                    "endRange": 67112048,
                    "durationSec": 5.338666666666667,
                    "startTimeSec": 21.354666666666667
                },
                {
                    "size": 13803077,
                    "type": 0,
                    "offset": 67112049,
                    "duration": 160160,
                    "time": 800800,
                    "timescale": 30000,
                    "mediaRange": "67112049-80915125",
                    "startRange": 67112049,
                    "endRange": 80915125,
                    "durationSec": 5.338666666666667,
                    "startTimeSec": 26.69333333333333
                },
                {
                    "size": 11307639,
                    "type": 0,
                    "offset": 80915126,
                    "duration": 160160,
                    "time": 960960,
                    "timescale": 30000,
                    "mediaRange": "80915126-92222764",
                    "startRange": 80915126,
                    "endRange": 92222764,
                    "durationSec": 5.338666666666667,
                    "startTimeSec": 32.032
                },
                {
                    "size": 14639124,
                    "type": 0,
                    "offset": 92222765,
                    "duration": 160160,
                    "time": 1121120,
                    "timescale": 30000,
                    "mediaRange": "92222765-106861888",
                    "startRange": 92222765,
                    "endRange": 106861888,
                    "durationSec": 5.338666666666667,
                    "startTimeSec": 37.370666666666665
                },
                {
                    "size": 14627026,
                    "type": 0,
                    "offset": 106861889,
                    "duration": 160160,
                    "time": 1281280,
                    "timescale": 30000,
                    "mediaRange": "106861889-121488914",
                    "startRange": 106861889,
                    "endRange": 121488914,
                    "durationSec": 5.338666666666667,
                    "startTimeSec": 42.70933333333333
                },
                {
                    "size": 14610857,
                    "type": 0,
                    "offset": 121488915,
                    "duration": 160160,
                    "time": 1441440,
                    "timescale": 30000,
                    "mediaRange": "121488915-136099771",
                    "startRange": 121488915,
                    "endRange": 136099771,
                    "durationSec": 5.338666666666667,
                    "startTimeSec": 48.048
                },
                {
                    "size": 14643146,
                    "type": 0,
                    "offset": 136099772,
                    "duration": 160160,
                    "time": 1601600,
                    "timescale": 30000,
                    "mediaRange": "136099772-150742917",
                    "startRange": 136099772,
                    "endRange": 150742917,
                    "durationSec": 5.338666666666667,
                    "startTimeSec": 53.38666666666666
                },
                {
                    "size": 14647610,
                    "type": 0,
                    "offset": 150742918,
                    "duration": 160160,
                    "time": 1761760,
                    "timescale": 30000,
                    "mediaRange": "150742918-165390527",
                    "startRange": 150742918,
                    "endRange": 165390527,
                    "durationSec": 5.338666666666667,
                    "startTimeSec": 58.72533333333333
                },
                {
                    "size": 14679492,
                    "type": 0,
                    "offset": 165390528,
                    "duration": 160160,
                    "time": 1921920,
                    "timescale": 30000,
                    "mediaRange": "165390528-180070019",
                    "startRange": 165390528,
                    "endRange": 180070019,
                    "durationSec": 5.338666666666667,
                    "startTimeSec": 64.064
                },
                {
                    "size": 14665934,
                    "type": 0,
                    "offset": 180070020,
                    "duration": 160160,
                    "time": 2082080,
                    "timescale": 30000,
                    "mediaRange": "180070020-194735953",
                    "startRange": 180070020,
                    "endRange": 194735953,
                    "durationSec": 5.338666666666667,
                    "startTimeSec": 69.40266666666666
                },
                {
                    "size": 14660685,
                    "type": 0,
                    "offset": 194735954,
                    "duration": 160160,
                    "time": 2242240,
                    "timescale": 30000,
                    "mediaRange": "194735954-209396638",
                    "startRange": 194735954,
                    "endRange": 209396638,
                    "durationSec": 5.338666666666667,
                    "startTimeSec": 74.74133333333333
                },
                {
                    "size": 14652516,
                    "type": 0,
                    "offset": 209396639,
                    "duration": 160160,
                    "time": 2402400,
                    "timescale": 30000,
                    "mediaRange": "209396639-224049154",
                    "startRange": 209396639,
                    "endRange": 224049154,
                    "durationSec": 5.338666666666667,
                    "startTimeSec": 80.08
                },
                {
                    "size": 14665352,
                    "type": 0,
                    "offset": 224049155,
                    "duration": 160160,
                    "time": 2562560,
                    "timescale": 30000,
                    "mediaRange": "224049155-238714506",
                    "startRange": 224049155,
                    "endRange": 238714506,
                    "durationSec": 5.338666666666667,
                    "startTimeSec": 85.41866666666667
                },
                {
                    "size": 14641925,
                    "type": 0,
                    "offset": 238714507,
                    "duration": 160160,
                    "time": 2722720,
                    "timescale": 30000,
                    "mediaRange": "238714507-253356431",
                    "startRange": 238714507,
                    "endRange": 253356431,
                    "durationSec": 5.338666666666667,
                    "startTimeSec": 90.75733333333334
                },
                {
                    "size": 14671647,
                    "type": 0,
                    "offset": 253356432,
                    "duration": 160160,
                    "time": 2882880,
                    "timescale": 30000,
                    "mediaRange": "253356432-268028078",
                    "startRange": 253356432,
                    "endRange": 268028078,
                    "durationSec": 5.338666666666667,
                    "startTimeSec": 96.096
                },
                {
                    "size": 14651414,
                    "type": 0,
                    "offset": 268028079,
                    "duration": 160160,
                    "time": 3043040,
                    "timescale": 30000,
                    "mediaRange": "268028079-282679492",
                    "startRange": 268028079,
                    "endRange": 282679492,
                    "durationSec": 5.338666666666667,
                    "startTimeSec": 101.43466666666667
                },
                {
                    "size": 14619811,
                    "type": 0,
                    "offset": 282679493,
                    "duration": 160160,
                    "time": 3203200,
                    "timescale": 30000,
                    "mediaRange": "282679493-297299303",
                    "startRange": 282679493,
                    "endRange": 297299303,
                    "durationSec": 5.338666666666667,
                    "startTimeSec": 106.77333333333333
                },
                {
                    "size": 14645227,
                    "type": 0,
                    "offset": 297299304,
                    "duration": 160160,
                    "time": 3363360,
                    "timescale": 30000,
                    "mediaRange": "297299304-311944530",
                    "startRange": 297299304,
                    "endRange": 311944530,
                    "durationSec": 5.338666666666667,
                    "startTimeSec": 112.112
                },
                {
                    "size": 14629543,
                    "type": 0,
                    "offset": 311944531,
                    "duration": 160160,
                    "time": 3523520,
                    "timescale": 30000,
                    "mediaRange": "311944531-326574073",
                    "startRange": 311944531,
                    "endRange": 326574073,
                    "durationSec": 5.338666666666667,
                    "startTimeSec": 117.45066666666666
                },
                {
                    "size": 14645523,
                    "type": 0,
                    "offset": 326574074,
                    "duration": 160160,
                    "time": 3683680,
                    "timescale": 30000,
                    "mediaRange": "326574074-341219596",
                    "startRange": 326574074,
                    "endRange": 341219596,
                    "durationSec": 5.338666666666667,
                    "startTimeSec": 122.78933333333333
                },
                {
                    "size": 14655538,
                    "type": 0,
                    "offset": 341219597,
                    "duration": 160160,
                    "time": 3843840,
                    "timescale": 30000,
                    "mediaRange": "341219597-355875134",
                    "startRange": 341219597,
                    "endRange": 355875134,
                    "durationSec": 5.338666666666667,
                    "startTimeSec": 128.128
                },
                {
                    "size": 14642529,
                    "type": 0,
                    "offset": 355875135,
                    "duration": 160160,
                    "time": 4004000,
                    "timescale": 30000,
                    "mediaRange": "355875135-370517663",
                    "startRange": 355875135,
                    "endRange": 370517663,
                    "durationSec": 5.338666666666667,
                    "startTimeSec": 133.46666666666667
                },
                {
                    "size": 14617233,
                    "type": 0,
                    "offset": 370517664,
                    "duration": 160160,
                    "time": 4164160,
                    "timescale": 30000,
                    "mediaRange": "370517664-385134896",
                    "startRange": 370517664,
                    "endRange": 385134896,
                    "durationSec": 5.338666666666667,
                    "startTimeSec": 138.80533333333332
                },
                {
                    "size": 14663858,
                    "type": 0,
                    "offset": 385134897,
                    "duration": 160160,
                    "time": 4324320,
                    "timescale": 30000,
                    "mediaRange": "385134897-399798754",
                    "startRange": 385134897,
                    "endRange": 399798754,
                    "durationSec": 5.338666666666667,
                    "startTimeSec": 144.144
                },
                {
                    "size": 14639208,
                    "type": 0,
                    "offset": 399798755,
                    "duration": 160160,
                    "time": 4484480,
                    "timescale": 30000,
                    "mediaRange": "399798755-414437962",
                    "startRange": 399798755,
                    "endRange": 414437962,
                    "durationSec": 5.338666666666667,
                    "startTimeSec": 149.48266666666666
                },
                {
                    "size": 14640174,
                    "type": 0,
                    "offset": 414437963,
                    "duration": 160160,
                    "time": 4644640,
                    "timescale": 30000,
                    "mediaRange": "414437963-429078136",
                    "startRange": 414437963,
                    "endRange": 429078136,
                    "durationSec": 5.338666666666667,
                    "startTimeSec": 154.82133333333334
                },
                {
                    "size": 14657878,
                    "type": 0,
                    "offset": 429078137,
                    "duration": 160160,
                    "time": 4804800,
                    "timescale": 30000,
                    "mediaRange": "429078137-443736014",
                    "startRange": 429078137,
                    "endRange": 443736014,
                    "durationSec": 5.338666666666667,
                    "startTimeSec": 160.16
                },
                {
                    "size": 14658296,
                    "type": 0,
                    "offset": 443736015,
                    "duration": 160160,
                    "time": 4964960,
                    "timescale": 30000,
                    "mediaRange": "443736015-458394310",
                    "startRange": 443736015,
                    "endRange": 458394310,
                    "durationSec": 5.338666666666667,
                    "startTimeSec": 165.49866666666668
                },
                {
                    "size": 14645778,
                    "type": 0,
                    "offset": 458394311,
                    "duration": 160160,
                    "time": 5125120,
                    "timescale": 30000,
                    "mediaRange": "458394311-473040088",
                    "startRange": 458394311,
                    "endRange": 473040088,
                    "durationSec": 5.338666666666667,
                    "startTimeSec": 170.83733333333333
                },
                {
                    "size": 14651220,
                    "type": 0,
                    "offset": 473040089,
                    "duration": 160160,
                    "time": 5285280,
                    "timescale": 30000,
                    "mediaRange": "473040089-487691308",
                    "startRange": 473040089,
                    "endRange": 487691308,
                    "durationSec": 5.338666666666667,
                    "startTimeSec": 176.176
                },
                {
                    "size": 14651528,
                    "type": 0,
                    "offset": 487691309,
                    "duration": 160160,
                    "time": 5445440,
                    "timescale": 30000,
                    "mediaRange": "487691309-502342836",
                    "startRange": 487691309,
                    "endRange": 502342836,
                    "durationSec": 5.338666666666667,
                    "startTimeSec": 181.51466666666667
                },
                {
                    "size": 14675086,
                    "type": 0,
                    "offset": 502342837,
                    "duration": 160160,
                    "time": 5605600,
                    "timescale": 30000,
                    "mediaRange": "502342837-517017922",
                    "startRange": 502342837,
                    "endRange": 517017922,
                    "durationSec": 5.338666666666667,
                    "startTimeSec": 186.85333333333332
                },
                {
                    "size": 14654752,
                    "type": 0,
                    "offset": 517017923,
                    "duration": 160160,
                    "time": 5765760,
                    "timescale": 30000,
                    "mediaRange": "517017923-531672674",
                    "startRange": 517017923,
                    "endRange": 531672674,
                    "durationSec": 5.338666666666667,
                    "startTimeSec": 192.192
                },
                {
                    "size": 14654595,
                    "type": 0,
                    "offset": 531672675,
                    "duration": 160160,
                    "time": 5925920,
                    "timescale": 30000,
                    "mediaRange": "531672675-546327269",
                    "startRange": 531672675,
                    "endRange": 546327269,
                    "durationSec": 5.338666666666667,
                    "startTimeSec": 197.53066666666666
                },
                {
                    "size": 14648399,
                    "type": 0,
                    "offset": 546327270,
                    "duration": 160160,
                    "time": 6086080,
                    "timescale": 30000,
                    "mediaRange": "546327270-560975668",
                    "startRange": 546327270,
                    "endRange": 560975668,
                    "durationSec": 5.338666666666667,
                    "startTimeSec": 202.86933333333334
                },
                {
                    "size": 14658953,
                    "type": 0,
                    "offset": 560975669,
                    "duration": 160160,
                    "time": 6246240,
                    "timescale": 30000,
                    "mediaRange": "560975669-575634621",
                    "startRange": 560975669,
                    "endRange": 575634621,
                    "durationSec": 5.338666666666667,
                    "startTimeSec": 208.208
                },
                {
                    "size": 14630598,
                    "type": 0,
                    "offset": 575634622,
                    "duration": 160160,
                    "time": 6406400,
                    "timescale": 30000,
                    "mediaRange": "575634622-590265219",
                    "startRange": 575634622,
                    "endRange": 590265219,
                    "durationSec": 5.338666666666667,
                    "startTimeSec": 213.54666666666665
                },
                {
                    "size": 14644493,
                    "type": 0,
                    "offset": 590265220,
                    "duration": 160160,
                    "time": 6566560,
                    "timescale": 30000,
                    "mediaRange": "590265220-604909712",
                    "startRange": 590265220,
                    "endRange": 604909712,
                    "durationSec": 5.338666666666667,
                    "startTimeSec": 218.88533333333334
                },
                {
                    "size": 14644854,
                    "type": 0,
                    "offset": 604909713,
                    "duration": 160160,
                    "time": 6726720,
                    "timescale": 30000,
                    "mediaRange": "604909713-619554566",
                    "startRange": 604909713,
                    "endRange": 619554566,
                    "durationSec": 5.338666666666667,
                    "startTimeSec": 224.224
                },
                {
                    "size": 14648429,
                    "type": 0,
                    "offset": 619554567,
                    "duration": 160160,
                    "time": 6886880,
                    "timescale": 30000,
                    "mediaRange": "619554567-634202995",
                    "startRange": 619554567,
                    "endRange": 634202995,
                    "durationSec": 5.338666666666667,
                    "startTimeSec": 229.56266666666667
                },
                {
                    "size": 14643442,
                    "type": 0,
                    "offset": 634202996,
                    "duration": 160160,
                    "time": 7047040,
                    "timescale": 30000,
                    "mediaRange": "634202996-648846437",
                    "startRange": 634202996,
                    "endRange": 648846437,
                    "durationSec": 5.338666666666667,
                    "startTimeSec": 234.90133333333333
                },
                {
                    "size": 14605171,
                    "type": 0,
                    "offset": 648846438,
                    "duration": 160160,
                    "time": 7207200,
                    "timescale": 30000,
                    "mediaRange": "648846438-663451608",
                    "startRange": 648846438,
                    "endRange": 663451608,
                    "durationSec": 5.338666666666667,
                    "startTimeSec": 240.24
                },
                {
                    "size": 14626375,
                    "type": 0,
                    "offset": 663451609,
                    "duration": 160160,
                    "time": 7367360,
                    "timescale": 30000,
                    "mediaRange": "663451609-678077983",
                    "startRange": 663451609,
                    "endRange": 678077983,
                    "durationSec": 5.338666666666667,
                    "startTimeSec": 245.57866666666666
                },
                {
                    "size": 14605429,
                    "type": 0,
                    "offset": 678077984,
                    "duration": 160160,
                    "time": 7527520,
                    "timescale": 30000,
                    "mediaRange": "678077984-692683412",
                    "startRange": 678077984,
                    "endRange": 692683412,
                    "durationSec": 5.338666666666667,
                    "startTimeSec": 250.91733333333335
                },
                {
                    "size": 14673021,
                    "type": 0,
                    "offset": 692683413,
                    "duration": 160160,
                    "time": 7687680,
                    "timescale": 30000,
                    "mediaRange": "692683413-707356433",
                    "startRange": 692683413,
                    "endRange": 707356433,
                    "durationSec": 5.338666666666667,
                    "startTimeSec": 256.256
                },
                {
                    "size": 14633728,
                    "type": 0,
                    "offset": 707356434,
                    "duration": 160160,
                    "time": 7847840,
                    "timescale": 30000,
                    "mediaRange": "707356434-721990161",
                    "startRange": 707356434,
                    "endRange": 721990161,
                    "durationSec": 5.338666666666667,
                    "startTimeSec": 261.5946666666667
                },
                {
                    "size": 14724110,
                    "type": 0,
                    "offset": 721990162,
                    "duration": 160160,
                    "time": 8008000,
                    "timescale": 30000,
                    "mediaRange": "721990162-736714271",
                    "startRange": 721990162,
                    "endRange": 736714271,
                    "durationSec": 5.338666666666667,
                    "startTimeSec": 266.93333333333334
                },
                {
                    "size": 14678030,
                    "type": 0,
                    "offset": 736714272,
                    "duration": 160160,
                    "time": 8168160,
                    "timescale": 30000,
                    "mediaRange": "736714272-751392301",
                    "startRange": 736714272,
                    "endRange": 751392301,
                    "durationSec": 5.338666666666667,
                    "startTimeSec": 272.272
                },
                {
                    "size": 14687346,
                    "type": 0,
                    "offset": 751392302,
                    "duration": 160160,
                    "time": 8328320,
                    "timescale": 30000,
                    "mediaRange": "751392302-766079647",
                    "startRange": 751392302,
                    "endRange": 766079647,
                    "durationSec": 5.338666666666667,
                    "startTimeSec": 277.61066666666665
                },
                {
                    "size": 14649775,
                    "type": 0,
                    "offset": 766079648,
                    "duration": 160160,
                    "time": 8488480,
                    "timescale": 30000,
                    "mediaRange": "766079648-780729422",
                    "startRange": 766079648,
                    "endRange": 780729422,
                    "durationSec": 5.338666666666667,
                    "startTimeSec": 282.94933333333336
                },
                {
                    "size": 14695118,
                    "type": 0,
                    "offset": 780729423,
                    "duration": 160160,
                    "time": 8648640,
                    "timescale": 30000,
                    "mediaRange": "780729423-795424540",
                    "startRange": 780729423,
                    "endRange": 795424540,
                    "durationSec": 5.338666666666667,
                    "startTimeSec": 288.288
                },
                {
                    "size": 14720259,
                    "type": 0,
                    "offset": 795424541,
                    "duration": 160160,
                    "time": 8808800,
                    "timescale": 30000,
                    "mediaRange": "795424541-810144799",
                    "startRange": 795424541,
                    "endRange": 810144799,
                    "durationSec": 5.338666666666667,
                    "startTimeSec": 293.62666666666667
                },
                {
                    "size": 14626890,
                    "type": 0,
                    "offset": 810144800,
                    "duration": 160160,
                    "time": 8968960,
                    "timescale": 30000,
                    "mediaRange": "810144800-824771689",
                    "startRange": 810144800,
                    "endRange": 824771689,
                    "durationSec": 5.338666666666667,
                    "startTimeSec": 298.9653333333333
                },
                {
                    "size": 14618873,
                    "type": 0,
                    "offset": 824771690,
                    "duration": 160160,
                    "time": 9129120,
                    "timescale": 30000,
                    "mediaRange": "824771690-839390562",
                    "startRange": 824771690,
                    "endRange": 839390562,
                    "durationSec": 5.338666666666667,
                    "startTimeSec": 304.304
                },
                {
                    "size": 14630800,
                    "type": 0,
                    "offset": 839390563,
                    "duration": 160160,
                    "time": 9289280,
                    "timescale": 30000,
                    "mediaRange": "839390563-854021362",
                    "startRange": 839390563,
                    "endRange": 854021362,
                    "durationSec": 5.338666666666667,
                    "startTimeSec": 309.6426666666667
                },
                {
                    "size": 14617969,
                    "type": 0,
                    "offset": 854021363,
                    "duration": 160160,
                    "time": 9449440,
                    "timescale": 30000,
                    "mediaRange": "854021363-868639331",
                    "startRange": 854021363,
                    "endRange": 868639331,
                    "durationSec": 5.338666666666667,
                    "startTimeSec": 314.98133333333334
                },
                {
                    "size": 11579349,
                    "type": 0,
                    "offset": 868639332,
                    "duration": 160160,
                    "time": 9609600,
                    "timescale": 30000,
                    "mediaRange": "868639332-880218680",
                    "startRange": 868639332,
                    "endRange": 880218680,
                    "durationSec": 5.338666666666667,
                    "startTimeSec": 320.32
                },
                {
                    "size": 14648494,
                    "type": 0,
                    "offset": 880218681,
                    "duration": 160160,
                    "time": 9769760,
                    "timescale": 30000,
                    "mediaRange": "880218681-894867174",
                    "startRange": 880218681,
                    "endRange": 894867174,
                    "durationSec": 5.338666666666667,
                    "startTimeSec": 325.65866666666665
                },
                {
                    "size": 14656214,
                    "type": 0,
                    "offset": 894867175,
                    "duration": 160160,
                    "time": 9929920,
                    "timescale": 30000,
                    "mediaRange": "894867175-909523388",
                    "startRange": 894867175,
                    "endRange": 909523388,
                    "durationSec": 5.338666666666667,
                    "startTimeSec": 330.99733333333336
                },
                {
                    "size": 14626621,
                    "type": 0,
                    "offset": 909523389,
                    "duration": 160160,
                    "time": 10090080,
                    "timescale": 30000,
                    "mediaRange": "909523389-924150009",
                    "startRange": 909523389,
                    "endRange": 924150009,
                    "durationSec": 5.338666666666667,
                    "startTimeSec": 336.336
                },
                {
                    "size": 14662238,
                    "type": 0,
                    "offset": 924150010,
                    "duration": 160160,
                    "time": 10250240,
                    "timescale": 30000,
                    "mediaRange": "924150010-938812247",
                    "startRange": 924150010,
                    "endRange": 938812247,
                    "durationSec": 5.338666666666667,
                    "startTimeSec": 341.67466666666667
                },
                {
                    "size": 14641726,
                    "type": 0,
                    "offset": 938812248,
                    "duration": 160160,
                    "time": 10410400,
                    "timescale": 30000,
                    "mediaRange": "938812248-953453973",
                    "startRange": 938812248,
                    "endRange": 953453973,
                    "durationSec": 5.338666666666667,
                    "startTimeSec": 347.0133333333333
                },
                {
                    "size": 14660945,
                    "type": 0,
                    "offset": 953453974,
                    "duration": 160160,
                    "time": 10570560,
                    "timescale": 30000,
                    "mediaRange": "953453974-968114918",
                    "startRange": 953453974,
                    "endRange": 968114918,
                    "durationSec": 5.338666666666667,
                    "startTimeSec": 352.352
                },
                {
                    "size": 14631702,
                    "type": 0,
                    "offset": 968114919,
                    "duration": 160160,
                    "time": 10730720,
                    "timescale": 30000,
                    "mediaRange": "968114919-982746620",
                    "startRange": 968114919,
                    "endRange": 982746620,
                    "durationSec": 5.338666666666667,
                    "startTimeSec": 357.6906666666667
                },
                {
                    "size": 14712709,
                    "type": 0,
                    "offset": 982746621,
                    "duration": 160160,
                    "time": 10890880,
                    "timescale": 30000,
                    "mediaRange": "982746621-997459329",
                    "startRange": 982746621,
                    "endRange": 997459329,
                    "durationSec": 5.338666666666667,
                    "startTimeSec": 363.02933333333334
                },
                {
                    "size": 14704205,
                    "type": 0,
                    "offset": 997459330,
                    "duration": 160160,
                    "time": 11051040,
                    "timescale": 30000,
                    "mediaRange": "997459330-1012163534",
                    "startRange": 997459330,
                    "endRange": 1012163534,
                    "durationSec": 5.338666666666667,
                    "startTimeSec": 368.368
                },
                {
                    "size": 14641125,
                    "type": 0,
                    "offset": 1012163535,
                    "duration": 160160,
                    "time": 11211200,
                    "timescale": 30000,
                    "mediaRange": "1012163535-1026804659",
                    "startRange": 1012163535,
                    "endRange": 1026804659,
                    "durationSec": 5.338666666666667,
                    "startTimeSec": 373.70666666666665
                },
                {
                    "size": 14642757,
                    "type": 0,
                    "offset": 1026804660,
                    "duration": 160160,
                    "time": 11371360,
                    "timescale": 30000,
                    "mediaRange": "1026804660-1041447416",
                    "startRange": 1026804660,
                    "endRange": 1041447416,
                    "durationSec": 5.338666666666667,
                    "startTimeSec": 379.04533333333336
                },
                {
                    "size": 14646427,
                    "type": 0,
                    "offset": 1041447417,
                    "duration": 160160,
                    "time": 11531520,
                    "timescale": 30000,
                    "mediaRange": "1041447417-1056093843",
                    "startRange": 1041447417,
                    "endRange": 1056093843,
                    "durationSec": 5.338666666666667,
                    "startTimeSec": 384.384
                },
                {
                    "size": 14661764,
                    "type": 0,
                    "offset": 1056093844,
                    "duration": 160160,
                    "time": 11691680,
                    "timescale": 30000,
                    "mediaRange": "1056093844-1070755607",
                    "startRange": 1056093844,
                    "endRange": 1070755607,
                    "durationSec": 5.338666666666667,
                    "startTimeSec": 389.72266666666667
                },
                {
                    "size": 14639025,
                    "type": 0,
                    "offset": 1070755608,
                    "duration": 160160,
                    "time": 11851840,
                    "timescale": 30000,
                    "mediaRange": "1070755608-1085394632",
                    "startRange": 1070755608,
                    "endRange": 1085394632,
                    "durationSec": 5.338666666666667,
                    "startTimeSec": 395.0613333333333
                },
                {
                    "size": 14669737,
                    "type": 0,
                    "offset": 1085394633,
                    "duration": 160160,
                    "time": 12012000,
                    "timescale": 30000,
                    "mediaRange": "1085394633-1100064369",
                    "startRange": 1085394633,
                    "endRange": 1100064369,
                    "durationSec": 5.338666666666667,
                    "startTimeSec": 400.4
                },
                {
                    "size": 8404130,
                    "type": 0,
                    "offset": 1100064370,
                    "duration": 160160,
                    "time": 12172160,
                    "timescale": 30000,
                    "mediaRange": "1100064370-1108468499",
                    "startRange": 1100064370,
                    "endRange": 1108468499,
                    "durationSec": 5.338666666666667,
                    "startTimeSec": 405.7386666666667
                },
                {
                    "size": 12650572,
                    "type": 0,
                    "offset": 1108468500,
                    "duration": 160160,
                    "time": 12332320,
                    "timescale": 30000,
                    "mediaRange": "1108468500-1121119071",
                    "startRange": 1108468500,
                    "endRange": 1121119071,
                    "durationSec": 5.338666666666667,
                    "startTimeSec": 411.07733333333334
                },
                {
                    "size": 13614524,
                    "type": 0,
                    "offset": 1121119072,
                    "duration": 160160,
                    "time": 12492480,
                    "timescale": 30000,
                    "mediaRange": "1121119072-1134733595",
                    "startRange": 1121119072,
                    "endRange": 1134733595,
                    "durationSec": 5.338666666666667,
                    "startTimeSec": 416.416
                },
                {
                    "size": 14672786,
                    "type": 0,
                    "offset": 1134733596,
                    "duration": 160160,
                    "time": 12652640,
                    "timescale": 30000,
                    "mediaRange": "1134733596-1149406381",
                    "startRange": 1134733596,
                    "endRange": 1149406381,
                    "durationSec": 5.338666666666667,
                    "startTimeSec": 421.75466666666665
                },
                {
                    "size": 14686408,
                    "type": 0,
                    "offset": 1149406382,
                    "duration": 160160,
                    "time": 12812800,
                    "timescale": 30000,
                    "mediaRange": "1149406382-1164092789",
                    "startRange": 1149406382,
                    "endRange": 1164092789,
                    "durationSec": 5.338666666666667,
                    "startTimeSec": 427.0933333333333
                },
                {
                    "size": 14665418,
                    "type": 0,
                    "offset": 1164092790,
                    "duration": 160160,
                    "time": 12972960,
                    "timescale": 30000,
                    "mediaRange": "1164092790-1178758207",
                    "startRange": 1164092790,
                    "endRange": 1178758207,
                    "durationSec": 5.338666666666667,
                    "startTimeSec": 432.432
                },
                {
                    "size": 14628392,
                    "type": 0,
                    "offset": 1178758208,
                    "duration": 160160,
                    "time": 13133120,
                    "timescale": 30000,
                    "mediaRange": "1178758208-1193386599",
                    "startRange": 1178758208,
                    "endRange": 1193386599,
                    "durationSec": 5.338666666666667,
                    "startTimeSec": 437.77066666666667
                },
                {
                    "size": 14662613,
                    "type": 0,
                    "offset": 1193386600,
                    "duration": 160160,
                    "time": 13293280,
                    "timescale": 30000,
                    "mediaRange": "1193386600-1208049212",
                    "startRange": 1193386600,
                    "endRange": 1208049212,
                    "durationSec": 5.338666666666667,
                    "startTimeSec": 443.1093333333333
                }
            ]
        }
    }
]